chafe-1.0.0.dist-info/top_level.txt
chafe-1.0.0.dist-info/RECORD
chafe-1.0.0.dist-info/LICENSE
chafe-1.0.0.dist-info/entry_points.txt
chafe-1.0.0.dist-info/METADATA
chafe-1.0.0.dist-info/WHEEL
_chacha/config.h
_chacha/machine.h
_chacha/portable.h
_chacha/_chacha.c
chacha/__init__.py
chacha/_chacha.cpython-311-x86_64-linux-gnu.so
chacha/view/__init__.py
chacha/view/__main__.py
chacha/encrypt/__init__.py
chacha/encrypt/__main__.py
chacha/decrypt/__init__.py
chacha/decrypt/__main__.py
