Metadata-Version: 2.1
Name: chafe
Version: 1.0.0
Summary: Encrypts and decrypts files using a pass phrase.
Author-email: Marc Culler <culler@users.noreply.github.com>
Maintainer-email: Marc Culler <culler@users.noreply.github.com>
Project-URL: Homepage, https://github.com/culler/chafe
Project-URL: Bug Tracker, https://github.com/culler/chafe/issues
Keywords: encrypt,decrypt,chacha
Classifier: Development Status :: 3 - Alpha
Classifier: Intended Audience :: End Users/Desktop
Classifier: Intended Audience :: Developers
Classifier: License :: OSI Approved :: MIT License
Classifier: Operating System :: OS Independent
Classifier: Programming Language :: Python
Classifier: Topic :: Utilities
Requires-Python: >=3.8
License-File: LICENSE
